kivycupertino/__init__.py
kivycupertino/app.py
kivycupertino/fonts/ny-bold-italic.otf
kivycupertino/fonts/ny-bold.otf
kivycupertino/fonts/ny-italic.ttf
kivycupertino/fonts/ny.ttf
kivycupertino/fonts/sf-bold-italic.otf
kivycupertino/fonts/sf-bold.otf
kivycupertino/fonts/sf-italic.otf
kivycupertino/fonts/sf.otf
kivycupertino/icons/info.png
kivycupertino/images/logo.png
kivycupertino/images/transparent.png
kivycupertino/init/fonts.py
kivycupertino/init/widgets.py
kivycupertino/uix/bar.py
kivycupertino/uix/button.py
kivycupertino/uix/control.py
kivycupertino/uix/dialog.py
kivycupertino/uix/indicator.py
kivycupertino/uix/label.py
kivycupertino/uix/switch.py
kivycupertino/uix/textfield.py
kivycupertino-0.0.1a0.dist-info/LICENSE
kivycupertino-0.0.1a0.dist-info/METADATA
kivycupertino-0.0.1a0.dist-info/WHEEL
kivycupertino-0.0.1a0.dist-info/top_level.txt
kivycupertino-0.0.1a0.dist-info/RECORD
