Metadata-Version: 2.1
Name: kivycupertino
Version: 0.0.1a0
Summary: iOS style widgets for Kivy
Home-page: https://github.com/cmdvmd/kivy-cupertino
Author: cmdmvd
Author-email: vcmd43@gmail.com
License: MIT
Project-URL: Documentation, https://kivy-cupertino.rtfd.io
Platform: UNKNOWN
Classifier: Development Status :: 3 - Alpha
Classifier: License :: OSI Approved :: MIT License
Classifier: Programming Language :: Python :: 3
Classifier: Programming Language :: Python :: 3.9
Classifier: Intended Audience :: Developers
Classifier: Intended Audience :: End Users/Desktop
Classifier: Operating System :: iOS
Classifier: Operating System :: MacOS
Classifier: Topic :: Scientific/Engineering :: Visualization
Classifier: Topic :: Software Development :: User Interfaces
Classifier: Topic :: Scientific/Engineering :: Human Machine Interfaces
Classifier: Topic :: Software Development :: Widget Sets
Requires-Dist: kivy
